cl/convince/__init__.py
cl/convince/settings.py
cl/convince/embedding/embedding_model.py
cl/convince/llm/gpt_lang_chain_llm.py
cl/convince/llm/gpt_native_llm.py
cl/convince/llm/llama_gpu_llm.py
cl/convince/llm/llama_lang_chain_llm.py
cl/convince/llm/llm.py
convince-0.0.2.dist-info/LICENSE
convince-0.0.2.dist-info/METADATA
convince-0.0.2.dist-info/WHEEL
convince-0.0.2.dist-info/top_level.txt
convince-0.0.2.dist-info/RECORD
