Metadata-Version: 2.1
Name: convince
Version: 0.0.2
Summary: Better instruction following for large language models
Home-page: https://github.com/compatibl/convince
Author: The Project Contributors
License: Apache Software License
Project-URL: Source Code, https://github.com/compatibl/convince
Classifier: Development Status :: 3 - Alpha
Classifier: Intended Audience :: Developers
Classifier: Intended Audience :: Science/Research
Classifier: Intended Audience :: Financial and Insurance Industry
Classifier: Topic :: Software Development
Classifier: Topic :: Scientific/Engineering
Classifier: License :: OSI Approved :: Apache Software License
Classifier: Programming Language :: Python :: 3.10
Classifier: Programming Language :: Python :: 3.11
Classifier: Programming Language :: Python :: 3.12
Classifier: Operating System :: OS Independent
License-File: LICENSE
Requires-Dist: aiohttp >=3.8.5
Requires-Dist: bokeh >=3.2.2
Requires-Dist: chromadb >=0.4.12
Requires-Dist: colorcet >=3.0.1
Requires-Dist: datashader >=0.15.2
Requires-Dist: exllamav2 >=0.0.5
Requires-Dist: faiss-cpu >=1.7.4
Requires-Dist: guidance >=0.0.64
Requires-Dist: holoviews >=1.17.1
Requires-Dist: huggingface-hub >=0.17.1
Requires-Dist: jsonformer >=0.12.0
Requires-Dist: langchain >=0.0.285
Requires-Dist: llama-cpp-python >=0.2.6
Requires-Dist: matplotlib >=3.8.0
Requires-Dist: numba >=0.58.0
Requires-Dist: numpy >=1.25.2
Requires-Dist: openai >=0.28.0
Requires-Dist: pandas >=2.1.1
Requires-Dist: protobuf >=4.24.3
Requires-Dist: pypdf >=3.16.2
Requires-Dist: python-dotenv >=1.0.0
Requires-Dist: scikit-image >=0.21.0
Requires-Dist: scikit-learn >=1.3.1
Requires-Dist: sentence-transformers >=2.2.2
Requires-Dist: sentencepiece >=0.1.99
Requires-Dist: tiktoken >=0.5.1
Requires-Dist: torch >=2.0.1
Requires-Dist: transformers >=4.33.2
Requires-Dist: umap-learn >=0.5.4
